{
  "kind": "collectionType",
  "collectionName": "doctors",
  "info": {
    "singularName": "doctor",
    "pluralName": "doctors",
    "displayName": "doctor"
  },
  "options": {
    "draftAndPublish": true
  },
  "pluginOptions": {},
  "attributes": {
    "name": {
      "type": "string"
    },
    "adress": {
      "type": "string"
    },
    "experince": {
      "type": "string"
    },
    "description": {
      "type": "string"
    },
    "Categorie": {
      "type": "string"
    },
    "img": {
      "type": "media",
      "multiple": true,
      "allowedTypes": [
        "images",
        "files",
        "videos",
        "audios"
      ]
    },
    "about": {
      "type": "string"
    }
  }
}
